{
  "project_info": {
    "project_number": "650759370682",
    "project_id": "firsteverythings"
  },
  "client": [
    {
      "client_info": {
        "mobilesdk_app_id": "1:650759370682:android:062d18c20603a137",
        "android_client_info": {
          "package_name": "com.ezayas.firsteverythings"
        }
      },
      "oauth_client": [],
      "api_key": [
        {
          "current_key": "AIzaSyBEbVVNWBItjfN1t44qfOCFNVg2Bz5CZO0"
        }
      ],
      "services": {
        "analytics_service": {
          "status": 2,
          "analytics_property": {
            "tracking_id": "UA-77104712-2"
          }
        },
        "appinvite_service": {
          "status": 1,
          "other_platform_oauth_client": []
        },
        "ads_service": {
          "status": 1
        }
      }
    }
  ],
  "configuration_version": "1"
}